odoo/addons/sale_order_line_packaging_qty/README.rst
odoo/addons/sale_order_line_packaging_qty/__init__.py
odoo/addons/sale_order_line_packaging_qty/__manifest__.py
odoo/addons/sale_order_line_packaging_qty/i18n/es.po
odoo/addons/sale_order_line_packaging_qty/i18n/sale_order_line_packaging_qty.pot
odoo/addons/sale_order_line_packaging_qty/models/__init__.py
odoo/addons/sale_order_line_packaging_qty/models/sale_order_line.py
odoo/addons/sale_order_line_packaging_qty/readme/CONTRIBUTORS.rst
odoo/addons/sale_order_line_packaging_qty/readme/DESCRIPTION.rst
odoo/addons/sale_order_line_packaging_qty/static/description/icon.png
odoo/addons/sale_order_line_packaging_qty/static/description/index.html
odoo/addons/sale_order_line_packaging_qty/tests/__init__.py
odoo/addons/sale_order_line_packaging_qty/tests/test_sale_order_line_packaging_qty.py
odoo/addons/sale_order_line_packaging_qty/views/sale_order.xml
odoo13_addon_sale_order_line_packaging_qty-13.0.1.3.2.dist-info/METADATA
odoo13_addon_sale_order_line_packaging_qty-13.0.1.3.2.dist-info/WHEEL
odoo13_addon_sale_order_line_packaging_qty-13.0.1.3.2.dist-info/top_level.txt
odoo13_addon_sale_order_line_packaging_qty-13.0.1.3.2.dist-info/RECORD
