Metadata-Version: 2.1
Name: odoo13-addon-sale-order-line-packaging-qty
Version: 13.0.1.3.2
Summary: Define quantities according to product packaging on sale order lines
Home-page: https://github.com/OCA/sale-workflow
Author: Camptocamp, Odoo Community Association (OCA)
Author-email: support@odoo-community.org
License: AGPL-3
Platform: UNKNOWN
Classifier: Programming Language :: Python
Classifier: Framework :: Odoo
Classifier: Framework :: Odoo :: 13.0
Classifier: License :: OSI Approved :: GNU Affero General Public License v3
Classifier: Development Status :: 5 - Production/Stable
Requires-Python: >=3.5
Requires-Dist: odoo <13.1dev,>=13.0a
